mycalc/calculator.py
minkyu0508-1.1.1.dist-info/METADATA
minkyu0508-1.1.1.dist-info/WHEEL
minkyu0508-1.1.1.dist-info/top_level.txt
minkyu0508-1.1.1.dist-info/RECORD
