Metadata-Version: 2.1
Name: minkyu0508
Version: 1.1.1
Summary: My Caclculator
Home-page: https://github.com/M1nKyu/mycalc
Download-URL: https://github.com/M1nKyu/mycalc
Author: minkyukang
License: UNKNOWN
Platform: UNKNOWN
Classifier: Programming Language :: Python :: 3
